b2sdk-2.10.2.dist-info/METADATA
b2sdk-2.10.2.dist-info/WHEEL
b2sdk-2.10.2.dist-info/entry_points.txt
b2sdk-2.10.2.dist-info/licenses/LICENSE
b2sdk/LICENSE
b2sdk/__init__.py
b2sdk/__main__.py
b2sdk/_internal/__init__.py
b2sdk/_internal/account_info/__init__.py
b2sdk/_internal/account_info/abstract.py
b2sdk/_internal/account_info/exception.py
b2sdk/_internal/account_info/in_memory.py
b2sdk/_internal/account_info/sqlite_account_info.py
b2sdk/_internal/account_info/stub.py
b2sdk/_internal/account_info/upload_url_pool.py
b2sdk/_internal/api.py
b2sdk/_internal/api_config.py
b2sdk/_internal/application_key.py
b2sdk/_internal/b2http.py
b2sdk/_internal/bounded_queue_executor.py
b2sdk/_internal/bucket.py
b2sdk/_internal/cache.py
b2sdk/_internal/encryption/__init__.py
b2sdk/_internal/encryption/setting.py
b2sdk/_internal/encryption/types.py
b2sdk/_internal/exception.py
b2sdk/_internal/file_lock.py
b2sdk/_internal/file_version.py
b2sdk/_internal/filter.py
b2sdk/_internal/http_constants.py
b2sdk/_internal/included_sources.py
b2sdk/_internal/large_file/__init__.py
b2sdk/_internal/large_file/part.py
b2sdk/_internal/large_file/services.py
b2sdk/_internal/large_file/unfinished_large_file.py
b2sdk/_internal/progress.py
b2sdk/_internal/raw_api.py
b2sdk/_internal/raw_simulator.py
b2sdk/_internal/replication/__init__.py
b2sdk/_internal/replication/monitoring.py
b2sdk/_internal/replication/setting.py
b2sdk/_internal/replication/setup.py
b2sdk/_internal/replication/types.py
b2sdk/_internal/requests/LICENSE
b2sdk/_internal/requests/NOTICE
b2sdk/_internal/requests/README.md
b2sdk/_internal/requests/__init__.py
b2sdk/_internal/requests/included_source_meta.py
b2sdk/_internal/scan/__init__.py
b2sdk/_internal/scan/exception.py
b2sdk/_internal/scan/folder.py
b2sdk/_internal/scan/folder_parser.py
b2sdk/_internal/scan/path.py
b2sdk/_internal/scan/policies.py
b2sdk/_internal/scan/report.py
b2sdk/_internal/scan/scan.py
b2sdk/_internal/session.py
b2sdk/_internal/stream/__init__.py
b2sdk/_internal/stream/base.py
b2sdk/_internal/stream/chained.py
b2sdk/_internal/stream/hashing.py
b2sdk/_internal/stream/progress.py
b2sdk-2.10.2.dist-info/RECORD
